sktan_cdk/__init__.py
sktan_cdk/single_page_app.py
sktan_cdk.single_page_app-0.1.0.dist-info/LICENSE
sktan_cdk.single_page_app-0.1.0.dist-info/METADATA
sktan_cdk.single_page_app-0.1.0.dist-info/WHEEL
sktan_cdk.single_page_app-0.1.0.dist-info/top_level.txt
sktan_cdk.single_page_app-0.1.0.dist-info/RECORD
