Metadata-Version: 2.1
Name: sktan-cdk.single-page-app
Version: 0.1.0
Summary: Base CDK stack for Single Page Applications
Home-page: https://github.com/sktan/aws-cdk-python-spa-base
Author: Steven Tan
Author-email: git@sktan.com
License: UNKNOWN
Platform: UNKNOWN
Classifier: Development Status :: 4 - Beta
Classifier: Intended Audience :: Developers
Classifier: License :: OSI Approved :: MIT License
Classifier: Programming Language :: JavaScript
Classifier: Programming Language :: Python :: 3 :: Only
Classifier: Programming Language :: Python :: 3.6
Classifier: Programming Language :: Python :: 3.7
Classifier: Programming Language :: Python :: 3.8
Classifier: Topic :: Software Development :: Code Generators
Classifier: Topic :: Utilities
Classifier: Typing :: Typed
Requires-Python: >=3.6
Requires-Dist: aws-cdk.core (>=1.22.0)
Requires-Dist: aws-cdk.aws-cloudfront (>=1.22.0)
Requires-Dist: aws-cdk.aws-s3 (>=1.22.0)
Requires-Dist: aws-cdk.aws-s3-deployment (>=1.22.0)
